richqueue/__init__.py
richqueue/console.py
richqueue/job.py
richqueue/layout.py
richqueue/log.py
richqueue/main.py
richqueue/slurm.py
richqueue/submit.py
richqueue/table.py
richqueue/tools.py
richqueue-1.11.2.dist-info/METADATA
richqueue-1.11.2.dist-info/WHEEL
richqueue-1.11.2.dist-info/entry_points.txt
richqueue-1.11.2.dist-info/licenses/LICENSE
richqueue-1.11.2.dist-info/RECORD
